{
  "generated_at": "2026-02-26T00:49:59.283366+00:00",
  "status": "success",
  "model": "prophet",
  "state": "United States",
  "metric": "weekly_deaths_all_cause",
  "horizon_weeks": 4,
  "last_known": {
    "date": "2023-08-19",
    "value": 54466
  },
  "forecast": [
    {
      "week_ending": "2023-08-20",
      "forecast": 56653,
      "lower_95": 47333,
      "upper_95": 65964
    },
    {
      "week_ending": "2023-08-27",
      "forecast": 57159,
      "lower_95": 47693,
      "upper_95": 66985
    },
    {
      "week_ending": "2023-09-03",
      "forecast": 57344,
      "lower_95": 48213,
      "upper_95": 66110
    },
    {
      "week_ending": "2023-09-10",
      "forecast": 57220,
      "lower_95": 47658,
      "upper_95": 67170
    }
  ],
  "trend": {
    "direction": "increasing",
    "pct_change": 1.0,
    "start_value": 56653,
    "end_value": 57220
  },
  "tarka_note": "Forecast generated by Prophet with 95% uncertainty intervals. Final 4 weeks of training data excluded due to known CDC reporting lag. Do not treat point estimates as ground truth \u2014 use interval bounds for planning."
}